make_subtitle/__init__.py
make_subtitle/make_subtitle.py
make_subtitle-0.0.3.dist-info/METADATA
make_subtitle-0.0.3.dist-info/WHEEL
make_subtitle-0.0.3.dist-info/top_level.txt
make_subtitle-0.0.3.dist-info/RECORD
